yamlu/__init__.py
yamlu/bb.py
yamlu/classification.py
yamlu/coco.py
yamlu/coco_read.py
yamlu/img.py
yamlu/img_ops.py
yamlu/misc.py
yamlu/np_utils.py
yamlu/ocr.py
yamlu/pandas_utils.py
yamlu/path.py
yamlu/polyline.py
yamlu/pytorch.py
yamlu/regression.py
yamlu/tsne.py
yamlu/voc.py
yamlu-0.0.17.dist-info/LICENSE.txt
yamlu-0.0.17.dist-info/METADATA
yamlu-0.0.17.dist-info/WHEEL
yamlu-0.0.17.dist-info/top_level.txt
yamlu-0.0.17.dist-info/RECORD
