Metadata-Version: 2.1
Name: yamlu
Version: 0.0.17
Summary: yet another machine learning utility library
Home-page: https://github.com/bernhardschaefer/yamlu/
Author: Bernhard Schäfer
Author-email: bernhard.schaefer1+pypi@gmail.com
License: Apache 2.0
Platform: any
Classifier: Development Status :: 4 - Beta
Classifier: Programming Language :: Python
Requires-Python: >=3.7
License-File: LICENSE.txt
Requires-Dist: matplotlib
Requires-Dist: numpy
Requires-Dist: Pillow
Requires-Dist: importlib-metadata ; python_version < "3.8"
Provides-Extra: all
Requires-Dist: scikit-learn ; extra == 'all'
Requires-Dist: pandas ; extra == 'all'
Requires-Dist: seaborn ; extra == 'all'
Requires-Dist: tqdm ; extra == 'all'
Requires-Dist: joblib ; extra == 'all'
Requires-Dist: torch ; extra == 'all'
Provides-Extra: testing
Requires-Dist: setuptools ; extra == 'testing'
Requires-Dist: pytest ; extra == 'testing'
